 [
  {"id":1,"name":"Lucasfilm Ltd."},
  {"id":2,"name":"Walt Disney Pictures"},
  {"id":3,"name":"Pixar"},
  {"id":4,"name":"Paramount Pictures"},
  {"id":5,"name":"Columbia Pictures"},
  {"id":6,"name":"RKO Radio Pictures"},
  {"id":7,"name":"DreamWorks Pictures"},
  {"id":8,"name":"Fine Line Features"},
  {"id":9,"name":"Gaumont"},
  {"id":10,"name":"Highlight"},
  {"id":11,"name":"WingNut Films"},
  {"id":12,"name":"New Line Cinema"},
  {"id":14,"name":"Miramax"},
  {"id":15,"name":"Lama Films"},
  {"id":16,"name":"United King Films"},
  {"id":17,"name":"Warner Bros. Entertainment"},
  {"id":18,"name":"Gracie Films"},
  {"id":19,"name":"Film Roman"},
  {"id":20,"name":"Rough Draft Studios"},
  {"id":21,"name":"Metro-Goldwyn-Mayer"},
  {"id":22,"name":"Alejandro González Iñárritu"},
  {"id":23,"name":"Imagine Entertainment"},
  {"id":24,"name":"Mikona Productions"},
  {"id":25,"name":"20th Century Fox"},
  {"id":26,"name":"Agustin Almodovar"},
  {"id":28,"name":"Newmarket Films"},
  {"id":29,"name":"Topcraft"},
  {"id":30,"name":"Eddie Murphy Productions"},
  {"id":31,"name":"Hamburger Filmschule"},
  {"id":32,"name":"Buena Vista Pictures"},
  {"id":33,"name":"Universal Pictures"},
  {"id":34,"name":"Sony Pictures"},
  {"id":35,"name":"Lions Gate Films"},
  {"id":37,"name":"Gramercy Pictures"},
  {"id":38,"name":"Studio Filmowe Tor"},
  {"id":39,"name":"Docurama"},
  {"id":40,"name":"Akira Committee Production"},
  {"id":41,"name":"Orion Pictures"},
  {"id":42,"name":"Universal Pictures Corporation"},
  {"id":43,"name":"Fox Searchlight Pictures"},
  {"id":44,"name":"Cruise/Wagner Productions"},
  {"id":45,"name":"Road Movies"},
  {"id":46,"name":"WDR"},
  {"id":47,"name":"Constantin Film"},
  {"id":48,"name":"Cristaldifilm S.r.l."},
  {"id":49,"name":"El Deseo"},
  {"id":50,"name":"Deutsche Vereinsfilm AG"},
  {"id":51,"name":"Fox Europa Produktion"},
  {"id":52,"name":"Film Polski Film Agency"},
  {"id":53,"name":"Les Films du Carrosse"},
  {"id":54,"name":"The Independent Film Channel Productions"},
  {"id":55,"name":"Decla Film Gesellschaft Holz & Co."},
  {"id":56,"name":"Amblin Entertainment"},
  {"id":57,"name":"Xenix Film"},
  {"id":58,"name":"Sony Pictures Classics"},
  {"id":59,"name":"A Band Apart"},
  {"id":60,"name":"United Artists"},
  {"id":62,"name":"The Selznick Studio"},
  {"id":64,"name":"Les Productions Artistes Associés"},
  {"id":65,"name":"Ulysse Production"},
  {"id":66,"name":"Town"},
  {"id":67,"name":"Unitec Films"},
  {"id":68,"name":"Big Primate Pictures"},
  {"id":69,"name":"MFPV Film"},
  {"id":70,"name":"American Zoetrope"},
  {"id":71,"name":"Elemental Films"},
  {"id":72,"name":"Valoria Films"},
  {"id":73,"name":"Fida Cinematografica"},
  {"id":74,"name":"Moovie"},
  {"id":75,"name":"Medienfonds German Film Productions GmbH & Co. KG"},
  {"id":76,"name":"Zentropa Entertainments"},
  {"id":77,"name":"Milestone Productions"},
  {"id":78,"name":"Hotshot Films"},
  {"id":79,"name":"Village Roadshow Pictures"},
  {"id":80,"name":"The Zanuck Company"},
  {"id":81,"name":"Plan B Entertainment"},
  {"id":82,"name":"Renn Productions"},
  {"id":83,"name":"France 2 Cinéma"},
  {"id":84,"name":"Tree Line Films"},
  {"id":85,"name":"Konrad Pictures"},
  {"id":86,"name":"Catfish Productions"},
  {"id":88,"name":"Hawk Films"},
  {"id":89,"name":"Augustus Film"},
  {"id":90,"name":"Tartan Films"},
  {"id":91,"name":"Lama Productions"},
  {"id":93,"name":"Lumer Films"},
  {"id":94,"name":"ARTE France Cinéma"},
  {"id":95,"name":"Hazazah Film"},
  {"id":96,"name":"X Filme Creative Pool"},
  {"id":97,"name":"Castle Rock Entertainment"},
  {"id":98,"name":"Detour Film Production"},
  {"id":99,"name":"OLGA FILM"},
  {"id":100,"name":"Avon Productions"},
  {"id":101,"name":"Roxy Film"},
  {"id":102,"name":"CJD"},
  {"id":104,"name":"Canal+"},
  {"id":105,"name":"CiBy 2000"},
  {"id":107,"name":"Mr. Brown Entertainment"},
  {"id":108,"name":"Concordia"},
  {"id":109,"name":"Rome-Paris Films"},
  {"id":110,"name":"Impéria"},
  {"id":111,"name":"miko-film"},
  {"id":113,"name":"Svenska Ord"},
  {"id":115,"name":"FilmTeknik"},
  {"id":116,"name":"Cameo Film- und Fernsehproduktion"},
  {"id":117,"name":"Kunsthochschule für Medien Köln"},
  {"id":118,"name":"Det Danske Filminstitut"},
  {"id":119,"name":"DR"},
  {"id":120,"name":"Scorsese Productions"},
  {"id":121,"name":"Y3 Film"},
  {"id":122,"name":"Coop99 Filmproduktion"},
  {"id":123,"name":"Trust Film"},
  {"id":124,"name":"SWR"},
  {"id":126,"name":"Lakeshore Entertainment"},
  {"id":128,"name":"Time Warner"},
  {"id":129,"name":"Section Eight"},
  {"id":130,"name":"Jerry Bruckheimer Films"},
  {"id":131,"name":"Bender-Spink Inc."},
  {"id":132,"name":"Big Sky Motion Picture"},
  {"id":133,"name":"North Fork Motion Picture"},
  {"id":134,"name":"Rogue Pictures"},
  {"id":136,"name":"City Light Films"},
  {"id":137,"name":"Great American Films Limited Partnership"},
  {"id":138,"name":"Schramm Film"},
  {"id":139,"name":"LJ Film"},
  {"id":140,"name":"Pandora Film"},
  {"id":141,"name":"Véra Films"},
  {"id":142,"name":"Silver Films"},
  {"id":143,"name":"CICC"},
  {"id":144,"name":"Fono Roma"},
  {"id":145,"name":"Gaumont Columbia Tristar Films"},
  {"id":146,"name":"Handmade Films"},
  {"id":147,"name":"Fidélité Productions"},
  {"id":148,"name":"Gimages"},
  {"id":149,"name":"FOZ"},
  {"id":150,"name":"Headforce Ltd."},
  {"id":151,"name":"Marquis Film"},
  {"id":152,"name":"Icon Productions"},
  {"id":153,"name":"Minerva Film"},
  {"id":154,"name":"Hall & Wallis Productions"},
  {"id":155,"name":"Nimbus Film"},
  {"id":156,"name":"Søren Stærmose"},
  {"id":157,"name":"SVT Drama"},
  {"id":158,"name":"Spyglass Entertainment"},
  {"id":159,"name":"Shady Acres Entertainment"},
  {"id":160,"name":"Pit Bull Productions"},
  {"id":161,"name":"Claussen+Wöbke Filmproduktion"},
  {"id":162,"name":"BR"},
  {"id":163,"name":"Revolution Films"},
  {"id":164,"name":"Rhombus Media"},
  {"id":165,"name":"Steen Herdel Filmproduktion"},
  {"id":166,"name":"Peter Rommel Productions"},
  {"id":167,"name":"Deblokada"},
  {"id":168,"name":"Jadran Film"},
  {"id":169,"name":"Noirfilm Filmproduktion"},
  {"id":170,"name":"Eve Productions Inc."},
  {"id":171,"name":"Malpaso Productions"},
  {"id":172,"name":"NPV Entertainment"},
  {"id":173,"name":"Village Productions"},
  {"id":174,"name":"Warner Bros. Pictures"},
  {"id":175,"name":"Caravan Pictures"},
  {"id":176,"name":"Different Tree Same Wood Productions"},
  {"id":177,"name":"Columbia TriStar"},
  {"id":178,"name":"Ghoulardi Film Company"},
  {"id":179,"name":"The Magnolia Project"},
  {"id":181,"name":"Channel Four Films"},
  {"id":182,"name":"JVC"},
  {"id":183,"name":"Le Studio Canal+"},
  {"id":184,"name":"Locus Solus Entertainment"},
  {"id":185,"name":"Pandora Cinema"},
  {"id":186,"name":"Pyramide Productions"},
  {"id":187,"name":"Victor Musical Industries, Inc."},
  {"id":188,"name":"Big Beach"},
  {"id":189,"name":"ARP Sélection"},
  {"id":190,"name":"Alice Productions"},
  {"id":191,"name":"Senator Film"},
  {"id":192,"name":"Shochiku"},
  {"id":193,"name":"Excelsa Film"},
  {"id":194,"name":"Hobby Films"},
  {"id":195,"name":"Pole Star"},
  {"id":196,"name":"Filmstudio Berlin"},
  {"id":197,"name":"Rommel Film"},
  {"id":198,"name":"GFP Medienfonds"},
  {"id":199,"name":"3 Sat"},
  {"id":200,"name":"Corazón International"}
  
  
  ]
  